adcm_version/__init__.py
adcm_version/utils.py
adcm_version-2.0.0.dist-info/METADATA
adcm_version-2.0.0.dist-info/WHEEL
adcm_version-2.0.0.dist-info/RECORD
