Metadata-Version: 2.4
Name: adcm-version
Version: 2.0.0
Summary: 
Author: Alexandr Alferov
Author-email: aas@arenadata.io
Requires-Python: >=3.8,<4.0
Classifier: Programming Language :: Python :: 3
Classifier: Programming Language :: Python :: 3.8
Classifier: Programming Language :: Python :: 3.9
Classifier: Programming Language :: Python :: 3.10
Classifier: Programming Language :: Python :: 3.11
Classifier: Programming Language :: Python :: 3.12
Classifier: Programming Language :: Python :: 3.13
Classifier: Programming Language :: Python :: 3.14
Requires-Dist: version-utils (>=0.3.2,<0.4.0)
